setup.py
swiftdownload.py
swiftdownload.egg-info/PKG-INFO
swiftdownload.egg-info/SOURCES.txt
swiftdownload.egg-info/dependency_links.txt
swiftdownload.egg-info/entry_points.txt
swiftdownload.egg-info/requires.txt
swiftdownload.egg-info/top_level.txt