Metadata-Version: 1.1
Name: swiftdownload
Version: 1.0.8
Summary: Python script which helps to download objects from object store using click
Home-page: https://gecgithub01.walmart.com/s0m03fe/swift-click-download
Author: Sunil Muliki
Author-email: Sunil.Muliki0@walmart.com
License: UNKNOWN
Platform: UNKNOWN
Classifier: License :: OSI Approved :: MIT License
Classifier: Operating System :: OS Independent
